titanicpackagegna/__init__.py
titanicpackagegna/controler.py
titanicpackagegna/get_data.py
titanicpackagegna/model.py
titanicpackagegna/pipeline.py
titanicpackagegna/preprocessing.py
titanicpackagegna/response_json.py
titanicpackagegna/tests.py
itanicpackagegna-0.0.4.dist-info/LICENSE
itanicpackagegna-0.0.4.dist-info/METADATA
itanicpackagegna-0.0.4.dist-info/WHEEL
itanicpackagegna-0.0.4.dist-info/top_level.txt
itanicpackagegna-0.0.4.dist-info/RECORD
