Metadata-Version: 2.1
Name: itanicpackagegna
Version: 0.0.4
Summary: Notre premier package de machine learning
Author: Nouha, Adrien, Gwendelina
Author-email: <gwendelina.prudhomme@gmail.com>
Keywords: python,titanic,ml,prediction,machine learning
Classifier: Development Status :: 1 - Planning
Classifier: Intended Audience :: Developers
Classifier: Programming Language :: Python :: 3
Classifier: Operating System :: Unix
Classifier: Operating System :: MacOS :: MacOS X
Classifier: Operating System :: Microsoft :: Windows
License-File: LICENSE
